mimir_cli/__init__.py
mimir_cli/globals.py
mimir_cli/mimir.py
mimir_cli/strings.py
mimir_cli/utils/__init__.py
mimir_cli/utils/auth.py
mimir_cli/utils/io.py
mimir_cli/utils/projects.py
mimir_cli/utils/submit.py
mimir_cli-0.5.3.dist-info/DESCRIPTION.rst
mimir_cli-0.5.3.dist-info/METADATA
mimir_cli-0.5.3.dist-info/RECORD
mimir_cli-0.5.3.dist-info/WHEEL
mimir_cli-0.5.3.dist-info/entry_points.txt
mimir_cli-0.5.3.dist-info/metadata.json
mimir_cli-0.5.3.dist-info/namespace_packages.txt
mimir_cli-0.5.3.dist-info/top_level.txt
