Metadata-Version: 2.0
Name: mimir-cli
Version: 0.5.3
Summary: mimir cli application
Home-page: UNKNOWN
Author: Jacobi Petrucciani
Author-email: jacobi@mimirhq.com
License: UNKNOWN
Platform: Any
Classifier: Programming Language :: Python
Classifier: Programming Language :: Python :: 2.7
Classifier: Programming Language :: Python :: 3.4
Classifier: Intended Audience :: Developers
Classifier: Environment :: Console
Requires-Dist: click
Requires-Dist: requests
